{
  "id": "cobblemon:alcremie#Lemon-Cream",
  "namespace": "cobblemon",
  "slug": "alcremie-lemon-cream",
  "name": "Alcremie Lemon-Cream",
  "nationalPokedexNumber": 869,
  "primaryType": "fairy",
  "secondaryType": null,
  "types": [
    "fairy"
  ],
  "baseStats": {
    "hp": 65,
    "attack": 60,
    "defence": 75,
    "special_attack": 110,
    "special_defence": 121,
    "speed": 64
  },
  "baseStatTotal": 495,
  "abilities": [
    "sweetveil",
    "sweetdish"
  ],
  "hiddenAbilities": [
    "aromaveil"
  ],
  "eggGroups": [
    "fairy",
    "amorphous"
  ],
  "catchRate": 100,
  "eggCycles": 20,
  "baseFriendship": 50,
  "height": 3,
  "weight": 5,
  "maleRatio": 0,
  "experienceGroup": "medium_fast",
  "baseExperienceYield": 173,
  "labels": [
    "gen8"
  ],
  "aspects": [
    "cream-lemon"
  ],
  "forms": [],
  "battleOnly": false,
  "pokedexDescription": "The moment it evolved, it took on a sour flavor. This is because of the way its cells spontaneously shifted during evolution.",
  "moveset": {
    "levelUp": [
      {
        "moveId": "decorate",
        "level": 1
      },
      {
        "moveId": "tackle",
        "level": 1
      },
      {
        "moveId": "absorb",
        "level": 1
      },
      {
        "moveId": "aromaticmist",
        "level": 1
      },
      {
        "moveId": "sweetkiss",
        "level": 1
      },
      {
        "moveId": "sweetscent",
        "level": 1
      },
      {
        "moveId": "aromatherapy",
        "level": 1
      },
      {
        "moveId": "drainingkiss",
        "level": 15
      },
      {
        "moveId": "charm",
        "level": 20
      },
      {
        "moveId": "attract",
        "level": 25
      },
      {
        "moveId": "acidarmor",
        "level": 30
      },
      {
        "moveId": "dazzlinggleam",
        "level": 35
      },
      {
        "moveId": "recover",
        "level": 40
      },
      {
        "moveId": "mistyterrain",
        "level": 45
      },
      {
        "moveId": "softserve",
        "level": 45
      },
      {
        "moveId": "entrainment",
        "level": 50
      },
      {
        "moveId": "sugarcrash",
        "level": 55
      }
    ],
    "egg": [
      {
        "moveId": "babydolleyes"
      },
      {
        "moveId": "lastresort"
      },
      {
        "moveId": "magictrick"
      }
    ],
    "tm": [
      {
        "moveId": "alluringvoice"
      },
      {
        "moveId": "attract"
      },
      {
        "moveId": "babydolleyes"
      },
      {
        "moveId": "calmmind"
      },
      {
        "moveId": "charm"
      },
      {
        "moveId": "dazzlinggleam"
      },
      {
        "moveId": "disarmingvoice"
      },
      {
        "moveId": "drainpunch"
      },
      {
        "moveId": "drainingkiss"
      },
      {
        "moveId": "encore"
      },
      {
        "moveId": "endeavor"
      },
      {
        "moveId": "endure"
      },
      {
        "moveId": "energyball"
      },
      {
        "moveId": "facade"
      },
      {
        "moveId": "faketears"
      },
      {
        "moveId": "firepunch"
      },
      {
        "moveId": "fling"
      },
      {
        "moveId": "gigadrain"
      },
      {
        "moveId": "gigaimpact"
      },
      {
        "moveId": "helpinghand"
      },
      {
        "moveId": "hyperbeam"
      },
      {
        "moveId": "icepunch"
      },
      {
        "moveId": "icywind"
      },
      {
        "moveId": "imprison"
      },
      {
        "moveId": "lastresort"
      },
      {
        "moveId": "lightscreen"
      },
      {
        "moveId": "magicroom"
      },
      {
        "moveId": "magicalleaf"
      },
      {
        "moveId": "metronome"
      },
      {
        "moveId": "mindbend"
      },
      {
        "moveId": "mistyexplosion"
      },
      {
        "moveId": "mistyterrain"
      },
      {
        "moveId": "mysticalfire"
      },
      {
        "moveId": "painsplit"
      },
      {
        "moveId": "playrough"
      },
      {
        "moveId": "protect"
      },
      {
        "moveId": "psychup"
      },
      {
        "moveId": "psychic"
      },
      {
        "moveId": "psyshock"
      },
      {
        "moveId": "rest"
      },
      {
        "moveId": "safeguard"
      },
      {
        "moveId": "sleeptalk"
      },
      {
        "moveId": "solarbeam"
      },
      {
        "moveId": "starshower"
      },
      {
        "moveId": "storedpower"
      },
      {
        "moveId": "substitute"
      },
      {
        "moveId": "terablast"
      },
      {
        "moveId": "thunderpunch"
      },
      {
        "moveId": "triattack"
      },
      {
        "moveId": "wonderroom"
      }
    ],
    "tutor": [
      {
        "moveId": "babydolleyes"
      },
      {
        "moveId": "calmmind"
      },
      {
        "moveId": "dazzlinggleam"
      },
      {
        "moveId": "drainpunch"
      },
      {
        "moveId": "endeavor"
      },
      {
        "moveId": "energyball"
      },
      {
        "moveId": "gigadrain"
      },
      {
        "moveId": "gigaimpact"
      },
      {
        "moveId": "helpinghand"
      },
      {
        "moveId": "hyperbeam"
      },
      {
        "moveId": "lastresort"
      },
      {
        "moveId": "magicroom"
      },
      {
        "moveId": "magicalleaf"
      },
      {
        "moveId": "mistyexplosion"
      },
      {
        "moveId": "mysticalfire"
      },
      {
        "moveId": "painsplit"
      },
      {
        "moveId": "playrough"
      },
      {
        "moveId": "psychic"
      },
      {
        "moveId": "rest"
      },
      {
        "moveId": "sleeptalk"
      },
      {
        "moveId": "wonderroom"
      }
    ],
    "legacy": [
      {
        "moveId": "round"
      },
      {
        "moveId": "snore"
      }
    ],
    "other": [
      {
        "moveId": "celebrate"
      }
    ]
  },
  "evolutions": [],
  "evolvesFrom": null,
  "matchup": {
    "weakTo": [
      {
        "type": "poison",
        "multiplier": 2
      },
      {
        "type": "steel",
        "multiplier": 2
      }
    ],
    "resists": [
      {
        "type": "bug",
        "multiplier": 0.5
      },
      {
        "type": "dark",
        "multiplier": 0.5
      },
      {
        "type": "fighting",
        "multiplier": 0.5
      }
    ],
    "immuneTo": [
      "dragon"
    ]
  },
  "image": {
    "kind": "render",
    "url": "/renders/alcremie-lemon-cream.png",
    "placeholderColor": "#D685AD"
  },
  "spawnInfo": [],
  "sourceMods": [
    "cobblemon-core",
    "lasers-additions"
  ],
  "primarySource": "cobblemon-core",
  "provenance": {
    "implemented": "cobblemon-core",
    "nationalPokedexNumber": "cobblemon-core",
    "name": "cobblemon-core",
    "primaryType": "cobblemon-core",
    "maleRatio": "cobblemon-core",
    "height": "cobblemon-core",
    "weight": "cobblemon-core",
    "pokedex": "cobblemon-core",
    "labels": "cobblemon-core",
    "aspects": "cobblemon-core",
    "abilities": "lasers-additions",
    "eggGroups": "cobblemon-core",
    "baseStats": "cobblemon-core",
    "evYield": "cobblemon-core",
    "baseExperienceYield": "cobblemon-core",
    "experienceGroup": "cobblemon-core",
    "catchRate": "cobblemon-core",
    "eggCycles": "cobblemon-core",
    "baseFriendship": "cobblemon-core",
    "shoulderMountable": "cobblemon-core",
    "baseScale": "cobblemon-core",
    "hitbox": "cobblemon-core",
    "behaviour": "cobblemon-core",
    "drops": "cobblemon-core",
    "moves": "lasers-additions",
    "preEvolution": "cobblemon-core",
    "evolutions": "cobblemon-core",
    "forms": "cobblemon-core"
  },
  "formOf": {
    "slug": "alcremie",
    "name": "Alcremie"
  },
  "formName": "Lemon-Cream"
}