{
  "id": "cobblemon:armillo",
  "namespace": "cobblemon",
  "slug": "armillo",
  "name": "Armillo",
  "nationalPokedexNumber": 1276,
  "primaryType": "ground",
  "secondaryType": null,
  "types": [
    "ground"
  ],
  "baseStats": {
    "hp": 55,
    "attack": 60,
    "defence": 120,
    "special_attack": 40,
    "special_defence": 101,
    "speed": 68
  },
  "baseStatTotal": 444,
  "abilities": [
    "sandrush",
    "bulletproof"
  ],
  "hiddenAbilities": [
    "steelworker"
  ],
  "eggGroups": [
    "field"
  ],
  "catchRate": 100,
  "eggCycles": 25,
  "baseFriendship": 50,
  "height": 5,
  "weight": 325,
  "maleRatio": 0.5,
  "experienceGroup": "medium_slow",
  "baseExperienceYield": 170,
  "labels": [
    "fakemon",
    "alatia"
  ],
  "aspects": [],
  "forms": [],
  "pokedexDescription": "It loves rolling at high speeds in flat and dry areas, and it will purposefully aim to run over any Digglets it sees poking out of the ground.",
  "moveset": {
    "levelUp": [
      {
        "moveId": "spinout",
        "level": 0
      },
      {
        "moveId": "metalclaw",
        "level": 0
      },
      {
        "moveId": "rollout",
        "level": 0
      },
      {
        "moveId": "sandattack",
        "level": 0
      },
      {
        "moveId": "defensecurl",
        "level": 0
      },
      {
        "moveId": "mudslap",
        "level": 0
      },
      {
        "moveId": "protect",
        "level": 0
      },
      {
        "moveId": "takedown",
        "level": 12
      },
      {
        "moveId": "bulldoze",
        "level": 18
      },
      {
        "moveId": "shellsmash",
        "level": 23
      },
      {
        "moveId": "gyroball",
        "level": 28
      },
      {
        "moveId": "irondefense",
        "level": 30
      },
      {
        "moveId": "highhorsepower",
        "level": 35
      },
      {
        "moveId": "ironhead",
        "level": 40
      },
      {
        "moveId": "doubleedge",
        "level": 45
      },
      {
        "moveId": "earthquake",
        "level": 50
      }
    ],
    "egg": [
      {
        "moveId": "accelerock"
      },
      {
        "moveId": "flamewheel"
      },
      {
        "moveId": "iceball"
      },
      {
        "moveId": "steamroller"
      },
      {
        "moveId": "wideguard"
      }
    ],
    "tm": [
      {
        "moveId": "acrobatics"
      },
      {
        "moveId": "batonpass"
      },
      {
        "moveId": "bodypress"
      },
      {
        "moveId": "bodyslam"
      },
      {
        "moveId": "bulkup"
      },
      {
        "moveId": "bulldoze"
      },
      {
        "moveId": "calmmind"
      },
      {
        "moveId": "counter"
      },
      {
        "moveId": "curse"
      },
      {
        "moveId": "cut"
      },
      {
        "moveId": "dig"
      },
      {
        "moveId": "doubleedge"
      },
      {
        "moveId": "earthquake"
      },
      {
        "moveId": "endeavor"
      },
      {
        "moveId": "endure"
      },
      {
        "moveId": "facade"
      },
      {
        "moveId": "falseswipe"
      },
      {
        "moveId": "flareblitz"
      },
      {
        "moveId": "furycutter"
      },
      {
        "moveId": "headbutt"
      },
      {
        "moveId": "highhorsepower"
      },
      {
        "moveId": "icespinner"
      },
      {
        "moveId": "lowkick"
      },
      {
        "moveId": "metalclaw"
      },
      {
        "moveId": "playrough"
      },
      {
        "moveId": "protect"
      },
      {
        "moveId": "rapidspin"
      },
      {
        "moveId": "rest"
      },
      {
        "moveId": "rockblast"
      },
      {
        "moveId": "rockpolish"
      },
      {
        "moveId": "rockslide"
      },
      {
        "moveId": "rocksmash"
      },
      {
        "moveId": "rocktomb"
      },
      {
        "moveId": "sandtomb"
      },
      {
        "moveId": "sandstorm"
      },
      {
        "moveId": "shadowclaw"
      },
      {
        "moveId": "sleeptalk"
      },
      {
        "moveId": "spikes"
      },
      {
        "moveId": "stealthrock"
      },
      {
        "moveId": "strength"
      },
      {
        "moveId": "substitute"
      },
      {
        "moveId": "supercellslam"
      },
      {
        "moveId": "takedown"
      },
      {
        "moveId": "terablast"
      },
      {
        "moveId": "trailblaze"
      },
      {
        "moveId": "tripleaxel"
      },
      {
        "moveId": "uturn"
      },
      {
        "moveId": "zenheadbutt"
      }
    ],
    "tutor": [
      {
        "moveId": "steelroller"
      }
    ],
    "legacy": [],
    "other": []
  },
  "evolutions": [
    {
      "targetKey": "cobblemon:bowldozer",
      "targetSlug": "bowldozer",
      "summary": "Usar protector",
      "variant": "item_interact"
    }
  ],
  "evolvesFrom": "rondidi",
  "matchup": {
    "weakTo": [
      {
        "type": "grass",
        "multiplier": 2
      },
      {
        "type": "ice",
        "multiplier": 2
      },
      {
        "type": "water",
        "multiplier": 2
      }
    ],
    "resists": [
      {
        "type": "poison",
        "multiplier": 0.5
      },
      {
        "type": "rock",
        "multiplier": 0.5
      }
    ],
    "immuneTo": [
      "electric"
    ]
  },
  "image": {
    "kind": "render",
    "url": "/renders/armillo.png",
    "placeholderColor": "#E2BF65"
  },
  "spawnInfo": [
    {
      "biomes": [
        "#cobblemon:is_savanna"
      ],
      "bucket": "common",
      "level": "30-50",
      "timeRange": null,
      "sourceId": "cobblemon-afp"
    },
    {
      "biomes": [
        "#cobblemon:is_badlands"
      ],
      "bucket": "common",
      "level": "30-50",
      "timeRange": null,
      "sourceId": "cobblemon-afp"
    }
  ],
  "sourceMods": [
    "cobblemon-afp"
  ],
  "primarySource": "cobblemon-afp",
  "provenance": {
    "implemented": "cobblemon-afp",
    "name": "cobblemon-afp",
    "nationalPokedexNumber": "cobblemon-afp",
    "primaryType": "cobblemon-afp",
    "abilities": "cobblemon-afp",
    "baseStats": "cobblemon-afp",
    "behaviour": "cobblemon-afp",
    "catchRate": "cobblemon-afp",
    "maleRatio": "cobblemon-afp",
    "shoulderMountable": "cobblemon-afp",
    "baseExperienceYield": "cobblemon-afp",
    "experienceGroup": "cobblemon-afp",
    "eggCycles": "cobblemon-afp",
    "eggGroups": "cobblemon-afp",
    "drops": "cobblemon-afp",
    "moves": "cobblemon-afp",
    "labels": "cobblemon-afp",
    "pokedex": "cobblemon-afp",
    "baseScale": "cobblemon-afp",
    "hitbox": "cobblemon-afp",
    "baseFriendship": "cobblemon-afp",
    "evYield": "cobblemon-afp",
    "height": "cobblemon-afp",
    "weight": "cobblemon-afp",
    "evolutions": "cobblemon-afp"
  }
}