{
  "id": "cobblemon:grubbee",
  "namespace": "cobblemon",
  "slug": "grubbee",
  "name": "Grubbee",
  "nationalPokedexNumber": 33,
  "primaryType": "normal",
  "secondaryType": "bug",
  "types": [
    "normal",
    "bug"
  ],
  "baseStats": {
    "hp": 85,
    "attack": 55,
    "defence": 55,
    "special_attack": 30,
    "special_defence": 65,
    "speed": 15
  },
  "baseStatTotal": 305,
  "abilities": [
    "honeypot"
  ],
  "hiddenAbilities": [],
  "eggGroups": [
    "field"
  ],
  "catchRate": 120,
  "eggCycles": 20,
  "baseFriendship": 50,
  "height": 5,
  "weight": 85,
  "maleRatio": 0.5,
  "experienceGroup": "medium_fast",
  "baseExperienceYield": 61,
  "labels": [
    "custom"
  ],
  "aspects": [],
  "forms": [],
  "pokedexDescription": "Grubbee are a ravenous species of Pokémon that often raid the hives of combee. They love the honey so much that they even choose to live in the hives that they raid, using the stored honey inside as food.",
  "moveset": {
    "levelUp": [
      {
        "moveId": "furycutter",
        "level": 1
      },
      {
        "moveId": "growl",
        "level": 1
      },
      {
        "moveId": "infestation",
        "level": 1
      },
      {
        "moveId": "sweetscent",
        "level": 3
      },
      {
        "moveId": "furyswipes",
        "level": 6
      },
      {
        "moveId": "bite",
        "level": 9
      },
      {
        "moveId": "playnice",
        "level": 12
      },
      {
        "moveId": "flail",
        "level": 15
      },
      {
        "moveId": "skittersmack",
        "level": 18
      },
      {
        "moveId": "slash",
        "level": 21
      },
      {
        "moveId": "followme",
        "level": 24
      },
      {
        "moveId": "yawn",
        "level": 27
      },
      {
        "moveId": "playrough",
        "level": 30
      },
      {
        "moveId": "thrash",
        "level": 33
      },
      {
        "moveId": "rest",
        "level": 36
      },
      {
        "moveId": "sleeptalk",
        "level": 36
      },
      {
        "moveId": "snore",
        "level": 36
      },
      {
        "moveId": "stickyweb",
        "level": 39
      },
      {
        "moveId": "gigaimpact",
        "level": 42
      }
    ],
    "egg": [
      {
        "moveId": "bellydrum"
      },
      {
        "moveId": "counter"
      },
      {
        "moveId": "fellstinger"
      },
      {
        "moveId": "headlongrush"
      },
      {
        "moveId": "nightslash"
      },
      {
        "moveId": "seismictoss"
      }
    ],
    "tm": [
      {
        "moveId": "agility"
      },
      {
        "moveId": "amnesia"
      },
      {
        "moveId": "attract"
      },
      {
        "moveId": "babydolleyes"
      },
      {
        "moveId": "bodyslam"
      },
      {
        "moveId": "bounce"
      },
      {
        "moveId": "brickbreak"
      },
      {
        "moveId": "brutalswing"
      },
      {
        "moveId": "bugbite"
      },
      {
        "moveId": "bugbuzz"
      },
      {
        "moveId": "bulkup"
      },
      {
        "moveId": "bulldoze"
      },
      {
        "moveId": "bulletseed"
      },
      {
        "moveId": "charm"
      },
      {
        "moveId": "confide"
      },
      {
        "moveId": "covet"
      },
      {
        "moveId": "crunch"
      },
      {
        "moveId": "curse"
      },
      {
        "moveId": "cut"
      },
      {
        "moveId": "dig"
      },
      {
        "moveId": "doubleteam"
      },
      {
        "moveId": "drainpunch"
      },
      {
        "moveId": "dualwingbeat"
      },
      {
        "moveId": "electroweb"
      },
      {
        "moveId": "embargo"
      },
      {
        "moveId": "endure"
      },
      {
        "moveId": "facade"
      },
      {
        "moveId": "faketears"
      },
      {
        "moveId": "fling"
      },
      {
        "moveId": "focuspunch"
      },
      {
        "moveId": "furycutter"
      },
      {
        "moveId": "gigadrain"
      },
      {
        "moveId": "gigaimpact"
      },
      {
        "moveId": "headbutt"
      },
      {
        "moveId": "helpinghand"
      },
      {
        "moveId": "honeclaws"
      },
      {
        "moveId": "hypervoice"
      },
      {
        "moveId": "icepunch"
      },
      {
        "moveId": "infestation"
      },
      {
        "moveId": "ironhead"
      },
      {
        "moveId": "leechlife"
      },
      {
        "moveId": "lowkick"
      },
      {
        "moveId": "lunge"
      },
      {
        "moveId": "megapunch"
      },
      {
        "moveId": "metalclaw"
      },
      {
        "moveId": "naturepower"
      },
      {
        "moveId": "playrough"
      },
      {
        "moveId": "pollenpuff"
      },
      {
        "moveId": "pounce"
      },
      {
        "moveId": "poweruppunch"
      },
      {
        "moveId": "protect"
      },
      {
        "moveId": "raindance"
      },
      {
        "moveId": "recycle"
      },
      {
        "moveId": "rest"
      },
      {
        "moveId": "retaliate"
      },
      {
        "moveId": "revenge"
      },
      {
        "moveId": "roar"
      },
      {
        "moveId": "rocksmash"
      },
      {
        "moveId": "rocktomb"
      },
      {
        "moveId": "rollout"
      },
      {
        "moveId": "roost"
      },
      {
        "moveId": "round"
      },
      {
        "moveId": "scaryface"
      },
      {
        "moveId": "shadowclaw"
      },
      {
        "moveId": "skittersmack"
      },
      {
        "moveId": "sleeptalk"
      },
      {
        "moveId": "snore"
      },
      {
        "moveId": "stompingtantrum"
      },
      {
        "moveId": "strength"
      },
      {
        "moveId": "stringshot"
      },
      {
        "moveId": "strugglebug"
      },
      {
        "moveId": "substitute"
      },
      {
        "moveId": "sunnyday"
      },
      {
        "moveId": "takedown"
      },
      {
        "moveId": "terablast"
      },
      {
        "moveId": "throatchop"
      },
      {
        "moveId": "thunderpunch"
      },
      {
        "moveId": "uturn"
      },
      {
        "moveId": "workup"
      },
      {
        "moveId": "xscissor"
      }
    ],
    "tutor": [],
    "legacy": [
      {
        "moveId": "attract"
      },
      {
        "moveId": "confide"
      },
      {
        "moveId": "doubleteam"
      },
      {
        "moveId": "frustration"
      },
      {
        "moveId": "hiddenpower"
      },
      {
        "moveId": "return"
      },
      {
        "moveId": "round"
      },
      {
        "moveId": "secretpower"
      },
      {
        "moveId": "snore"
      },
      {
        "moveId": "swagger"
      },
      {
        "moveId": "toxic"
      }
    ],
    "other": []
  },
  "evolutions": [
    {
      "targetKey": "cobblemon:mielador",
      "targetSlug": "mielador",
      "summary": "Nivel · Nv. 37",
      "variant": "level_up"
    }
  ],
  "evolvesFrom": null,
  "matchup": {
    "weakTo": [
      {
        "type": "fire",
        "multiplier": 2
      },
      {
        "type": "flying",
        "multiplier": 2
      },
      {
        "type": "rock",
        "multiplier": 2
      }
    ],
    "resists": [
      {
        "type": "grass",
        "multiplier": 0.5
      },
      {
        "type": "ground",
        "multiplier": 0.5
      }
    ],
    "immuneTo": [
      "ghost"
    ]
  },
  "image": {
    "kind": "render",
    "url": "/renders/grubbee.png",
    "placeholderColor": "#A8A77A"
  },
  "spawnInfo": [
    {
      "biomes": [
        "#cobblemon:is_forest",
        "#cobblemon:is_mountain",
        "aether:skyroot_forest",
        "aether:skyroot_woodland",
        "#cobblemon:is_taiga"
      ],
      "bucket": "common",
      "level": "8-33",
      "timeRange": null,
      "sourceId": "lively-mons"
    },
    {
      "biomes": [
        "#aether:is_aether",
        "#cobblemon:is_overworld"
      ],
      "bucket": "common",
      "level": "8-33",
      "timeRange": null,
      "sourceId": "lively-mons"
    },
    {
      "biomes": [
        "the_bumblezone:crystal_canyon",
        "the_bumblezone:floral_meadow"
      ],
      "bucket": "common",
      "level": "8-33",
      "timeRange": null,
      "sourceId": "lively-mons"
    }
  ],
  "sourceMods": [
    "lively-mons"
  ],
  "primarySource": "lively-mons",
  "provenance": {
    "implemented": "lively-mons",
    "nationalPokedexNumber": "lively-mons",
    "name": "lively-mons",
    "primaryType": "lively-mons",
    "secondaryType": "lively-mons",
    "maleRatio": "lively-mons",
    "height": "lively-mons",
    "weight": "lively-mons",
    "shoulderMountable": "lively-mons",
    "pokedex": "lively-mons",
    "labels": "lively-mons",
    "aspects": "lively-mons",
    "abilities": "lively-mons",
    "eggGroups": "lively-mons",
    "baseStats": "lively-mons",
    "evYield": "lively-mons",
    "baseExperienceYield": "lively-mons",
    "experienceGroup": "lively-mons",
    "catchRate": "lively-mons",
    "eggCycles": "lively-mons",
    "baseFriendship": "lively-mons",
    "baseScale": "lively-mons",
    "standingEyeHeight": "lively-mons",
    "swimmingEyeHeight": "lively-mons",
    "flyingEyeHeight": "lively-mons",
    "hitbox": "lively-mons",
    "behaviour": "lively-mons",
    "drops": "lively-mons",
    "moves": "lively-mons",
    "evolutions": "lively-mons"
  }
}