{
  "id": "cobblemon:panpour",
  "namespace": "cobblemon",
  "slug": "panpour",
  "name": "Panpour",
  "nationalPokedexNumber": 515,
  "primaryType": "water",
  "secondaryType": null,
  "types": [
    "water"
  ],
  "baseStats": {
    "hp": 50,
    "attack": 53,
    "defence": 48,
    "special_attack": 53,
    "special_defence": 48,
    "speed": 64
  },
  "baseStatTotal": 316,
  "abilities": [
    "gluttony",
    "torrent"
  ],
  "hiddenAbilities": [
    "liquify"
  ],
  "eggGroups": [
    "field"
  ],
  "catchRate": 190,
  "eggCycles": 20,
  "baseFriendship": 50,
  "height": 6,
  "weight": 135,
  "maleRatio": 0.875,
  "experienceGroup": "medium_fast",
  "baseExperienceYield": 63,
  "labels": [
    "gen5"
  ],
  "aspects": [],
  "forms": [],
  "pokedexDescription": "The water stored inside the tuft on its head is full of nutrients. Plants that receive its water grow large.",
  "moveset": {
    "levelUp": [
      {
        "moveId": "scratch",
        "level": 1
      },
      {
        "moveId": "quickattack",
        "level": 1
      },
      {
        "moveId": "fakeout",
        "level": 1
      },
      {
        "moveId": "aquaring",
        "level": 1
      },
      {
        "moveId": "watersport",
        "level": 1
      },
      {
        "moveId": "workup",
        "level": 1
      },
      {
        "moveId": "playnice",
        "level": 1
      },
      {
        "moveId": "leer",
        "level": 4
      },
      {
        "moveId": "lick",
        "level": 7
      },
      {
        "moveId": "watergun",
        "level": 10
      },
      {
        "moveId": "furyswipes",
        "level": 13
      },
      {
        "moveId": "bubblebeam",
        "level": 16
      },
      {
        "moveId": "bite",
        "level": 19
      },
      {
        "moveId": "scald",
        "level": 22
      },
      {
        "moveId": "taunt",
        "level": 25
      },
      {
        "moveId": "headbutt",
        "level": 28
      },
      {
        "moveId": "fling",
        "level": 28
      },
      {
        "moveId": "acrobatics",
        "level": 31
      },
      {
        "moveId": "hydropump",
        "level": 32
      },
      {
        "moveId": "brine",
        "level": 34
      },
      {
        "moveId": "crunch",
        "level": 36
      },
      {
        "moveId": "recycle",
        "level": 37
      },
      {
        "moveId": "focusblast",
        "level": 43
      },
      {
        "moveId": "naturalgift",
        "level": 46
      },
      {
        "moveId": "rockclimb",
        "level": 52
      }
    ],
    "egg": [
      {
        "moveId": "aquaring"
      },
      {
        "moveId": "aquatail"
      },
      {
        "moveId": "astonish"
      },
      {
        "moveId": "covet"
      },
      {
        "moveId": "disarmingvoice"
      },
      {
        "moveId": "hydropump"
      },
      {
        "moveId": "lowkick"
      },
      {
        "moveId": "mudsport"
      },
      {
        "moveId": "nastyplot"
      },
      {
        "moveId": "roleplay"
      },
      {
        "moveId": "tickle"
      }
    ],
    "tm": [
      {
        "moveId": "acrobatics"
      },
      {
        "moveId": "aquatail"
      },
      {
        "moveId": "blizzard"
      },
      {
        "moveId": "brine"
      },
      {
        "moveId": "covet"
      },
      {
        "moveId": "crunch"
      },
      {
        "moveId": "cut"
      },
      {
        "moveId": "dig"
      },
      {
        "moveId": "disarmingvoice"
      },
      {
        "moveId": "dive"
      },
      {
        "moveId": "endeavor"
      },
      {
        "moveId": "endure"
      },
      {
        "moveId": "facade"
      },
      {
        "moveId": "fling"
      },
      {
        "moveId": "flipturn"
      },
      {
        "moveId": "focuspunch"
      },
      {
        "moveId": "gastroacid"
      },
      {
        "moveId": "grassknot"
      },
      {
        "moveId": "gunkshot"
      },
      {
        "moveId": "hail"
      },
      {
        "moveId": "helpinghand"
      },
      {
        "moveId": "honeclaws"
      },
      {
        "moveId": "hydropump"
      },
      {
        "moveId": "icebeam"
      },
      {
        "moveId": "icepunch"
      },
      {
        "moveId": "icywind"
      },
      {
        "moveId": "irontail"
      },
      {
        "moveId": "knockoff"
      },
      {
        "moveId": "lowkick"
      },
      {
        "moveId": "lowsweep"
      },
      {
        "moveId": "nastyplot"
      },
      {
        "moveId": "naturalgift"
      },
      {
        "moveId": "payback"
      },
      {
        "moveId": "protect"
      },
      {
        "moveId": "raindance"
      },
      {
        "moveId": "recycle"
      },
      {
        "moveId": "rest"
      },
      {
        "moveId": "rocksmash"
      },
      {
        "moveId": "rocktomb"
      },
      {
        "moveId": "roleplay"
      },
      {
        "moveId": "scald"
      },
      {
        "moveId": "shadowclaw"
      },
      {
        "moveId": "sleeptalk"
      },
      {
        "moveId": "substitute"
      },
      {
        "moveId": "surf"
      },
      {
        "moveId": "swift"
      },
      {
        "moveId": "taunt"
      },
      {
        "moveId": "terablast"
      },
      {
        "moveId": "thief"
      },
      {
        "moveId": "torment"
      },
      {
        "moveId": "uproar"
      },
      {
        "moveId": "waterpledge"
      },
      {
        "moveId": "waterpulse"
      },
      {
        "moveId": "waterfall"
      },
      {
        "moveId": "workup"
      }
    ],
    "tutor": [
      {
        "moveId": "aquatail"
      },
      {
        "moveId": "covet"
      },
      {
        "moveId": "dive"
      },
      {
        "moveId": "endeavor"
      },
      {
        "moveId": "flipturn"
      },
      {
        "moveId": "focuspunch"
      },
      {
        "moveId": "gastroacid"
      },
      {
        "moveId": "gunkshot"
      },
      {
        "moveId": "helpinghand"
      },
      {
        "moveId": "icebeam"
      },
      {
        "moveId": "icepunch"
      },
      {
        "moveId": "icywind"
      },
      {
        "moveId": "irontail"
      },
      {
        "moveId": "knockoff"
      },
      {
        "moveId": "lowkick"
      },
      {
        "moveId": "recycle"
      },
      {
        "moveId": "rest"
      },
      {
        "moveId": "rocksmash"
      },
      {
        "moveId": "roleplay"
      },
      {
        "moveId": "shadowclaw"
      },
      {
        "moveId": "sleeptalk"
      },
      {
        "moveId": "swift"
      },
      {
        "moveId": "uproar"
      },
      {
        "moveId": "waterpledge"
      },
      {
        "moveId": "waterpulse"
      }
    ],
    "legacy": [
      {
        "moveId": "attract"
      },
      {
        "moveId": "confide"
      },
      {
        "moveId": "doubleteam"
      },
      {
        "moveId": "frustration"
      },
      {
        "moveId": "hiddenpower"
      },
      {
        "moveId": "return"
      },
      {
        "moveId": "round"
      },
      {
        "moveId": "secretpower"
      },
      {
        "moveId": "snore"
      },
      {
        "moveId": "swagger"
      },
      {
        "moveId": "toxic"
      }
    ],
    "other": []
  },
  "evolutions": [
    {
      "targetKey": "cobblemon:simipour",
      "targetSlug": "simipour",
      "summary": "Usar water_stone · (consume objeto sostenido)",
      "variant": "item_interact"
    }
  ],
  "evolvesFrom": null,
  "matchup": {
    "weakTo": [
      {
        "type": "electric",
        "multiplier": 2
      },
      {
        "type": "grass",
        "multiplier": 2
      }
    ],
    "resists": [
      {
        "type": "fire",
        "multiplier": 0.5
      },
      {
        "type": "ice",
        "multiplier": 0.5
      },
      {
        "type": "steel",
        "multiplier": 0.5
      },
      {
        "type": "water",
        "multiplier": 0.5
      }
    ],
    "immuneTo": []
  },
  "image": {
    "kind": "sprite",
    "url": "https://raw.githubusercontent.com/PokeAPI/sprites/master/sprites/pokemon/other/official-artwork/515.png"
  },
  "spawnInfo": [
    {
      "biomes": [
        "#cobblemon:is_jungle",
        "#cobblemon:is_tropical_island"
      ],
      "bucket": "uncommon",
      "level": "7-32",
      "timeRange": null,
      "sourceId": "cobblemon-core"
    },
    {
      "biomes": [
        "#cobblemon:is_river"
      ],
      "bucket": "uncommon",
      "level": "7-32",
      "timeRange": null,
      "sourceId": "cobblemon-core"
    },
    {
      "biomes": [
        "the_void"
      ],
      "bucket": "uncommon",
      "level": "7-32",
      "timeRange": null,
      "sourceId": "digimod"
    },
    {
      "biomes": [
        "the_void"
      ],
      "bucket": "uncommon",
      "level": "7-32",
      "timeRange": null,
      "sourceId": "digimod"
    },
    {
      "biomes": [
        "#cobblemon:is_jungle",
        "#cobblemon:is_tropical_island"
      ],
      "bucket": "uncommon",
      "level": "7-32",
      "timeRange": null,
      "sourceId": "digimod-spawn-together"
    },
    {
      "biomes": [
        "#cobblemon:is_river"
      ],
      "bucket": "uncommon",
      "level": "7-32",
      "timeRange": null,
      "sourceId": "digimod-spawn-together"
    }
  ],
  "sourceMods": [
    "cobblemon-core",
    "lasers-additions"
  ],
  "primarySource": "cobblemon-core",
  "provenance": {
    "implemented": "cobblemon-core",
    "nationalPokedexNumber": "cobblemon-core",
    "name": "cobblemon-core",
    "primaryType": "cobblemon-core",
    "maleRatio": "cobblemon-core",
    "height": "cobblemon-core",
    "weight": "cobblemon-core",
    "pokedex": "cobblemon-core",
    "labels": "cobblemon-core",
    "aspects": "cobblemon-core",
    "abilities": "lasers-additions",
    "eggGroups": "cobblemon-core",
    "baseStats": "cobblemon-core",
    "evYield": "cobblemon-core",
    "baseExperienceYield": "cobblemon-core",
    "experienceGroup": "cobblemon-core",
    "catchRate": "cobblemon-core",
    "eggCycles": "cobblemon-core",
    "baseFriendship": "cobblemon-core",
    "baseScale": "cobblemon-core",
    "hitbox": "cobblemon-core",
    "standingEyeHeight": "cobblemon-core",
    "drops": "cobblemon-core",
    "moves": "lasers-additions",
    "evolutions": "cobblemon-core",
    "behaviour": "cobblemon-core"
  }
}