{
  "id": "cobblemon:piloswine",
  "namespace": "cobblemon",
  "slug": "piloswine",
  "name": "Piloswine",
  "nationalPokedexNumber": 221,
  "primaryType": "ice",
  "secondaryType": "ground",
  "types": [
    "ice",
    "ground"
  ],
  "baseStats": {
    "hp": 100,
    "attack": 100,
    "defence": 80,
    "special_attack": 60,
    "special_defence": 60,
    "speed": 50
  },
  "baseStatTotal": 450,
  "abilities": [
    "oblivious",
    "snowforce"
  ],
  "hiddenAbilities": [
    "thickfat"
  ],
  "eggGroups": [
    "field"
  ],
  "catchRate": 75,
  "eggCycles": 20,
  "baseFriendship": 50,
  "height": 11,
  "weight": 558,
  "maleRatio": 0.5,
  "experienceGroup": "slow",
  "baseExperienceYield": 158,
  "labels": [
    "gen2"
  ],
  "aspects": [],
  "forms": [],
  "pokedexDescription": "Piloswine is covered by a thick coat of long hair that enables it to endure the freezing cold. This Pokémon uses its tusks to dig up food that has been buried under ice.",
  "moveset": {
    "levelUp": [
      {
        "moveId": "ancientpower",
        "level": 1
      },
      {
        "moveId": "peck",
        "level": 1
      },
      {
        "moveId": "odorsleuth",
        "level": 1
      },
      {
        "moveId": "mudsport",
        "level": 1
      },
      {
        "moveId": "powdersnow",
        "level": 1
      },
      {
        "moveId": "mudslap",
        "level": 1
      },
      {
        "moveId": "mudbomb",
        "level": 1
      },
      {
        "moveId": "icefang",
        "level": 1
      },
      {
        "moveId": "furyattack",
        "level": 1
      },
      {
        "moveId": "tackle",
        "level": 1
      },
      {
        "moveId": "flail",
        "level": 1
      },
      {
        "moveId": "iceshard",
        "level": 15
      },
      {
        "moveId": "mist",
        "level": 20
      },
      {
        "moveId": "endure",
        "level": 25
      },
      {
        "moveId": "icywind",
        "level": 30
      },
      {
        "moveId": "amnesia",
        "level": 37
      },
      {
        "moveId": "takedown",
        "level": 44
      },
      {
        "moveId": "earthquake",
        "level": 51
      },
      {
        "moveId": "blizzard",
        "level": 58
      },
      {
        "moveId": "thrash",
        "level": 65
      }
    ],
    "egg": [
      {
        "moveId": "ancientpower"
      },
      {
        "moveId": "bite"
      },
      {
        "moveId": "curse"
      },
      {
        "moveId": "doubleedge"
      },
      {
        "moveId": "fissure"
      },
      {
        "moveId": "freezedry"
      },
      {
        "moveId": "iciclecrash"
      },
      {
        "moveId": "mudbomb"
      }
    ],
    "tm": [
      {
        "moveId": "amnesia"
      },
      {
        "moveId": "ancientpower"
      },
      {
        "moveId": "avalanche"
      },
      {
        "moveId": "babydolleyes"
      },
      {
        "moveId": "blizzard"
      },
      {
        "moveId": "bodyslam"
      },
      {
        "moveId": "bulldoze"
      },
      {
        "moveId": "charm"
      },
      {
        "moveId": "curse"
      },
      {
        "moveId": "dig"
      },
      {
        "moveId": "doubleedge"
      },
      {
        "moveId": "earthpower"
      },
      {
        "moveId": "earthquake"
      },
      {
        "moveId": "endeavor"
      },
      {
        "moveId": "endure"
      },
      {
        "moveId": "facade"
      },
      {
        "moveId": "gigaimpact"
      },
      {
        "moveId": "hail"
      },
      {
        "moveId": "haze"
      },
      {
        "moveId": "headbutt"
      },
      {
        "moveId": "highhorsepower"
      },
      {
        "moveId": "hyperbeam"
      },
      {
        "moveId": "icebeam"
      },
      {
        "moveId": "icefang"
      },
      {
        "moveId": "iciclespear"
      },
      {
        "moveId": "icywind"
      },
      {
        "moveId": "mudshot"
      },
      {
        "moveId": "mudslap"
      },
      {
        "moveId": "protect"
      },
      {
        "moveId": "raindance"
      },
      {
        "moveId": "rest"
      },
      {
        "moveId": "reversal"
      },
      {
        "moveId": "roar"
      },
      {
        "moveId": "rockslide"
      },
      {
        "moveId": "rocksmash"
      },
      {
        "moveId": "rocktomb"
      },
      {
        "moveId": "sandtomb"
      },
      {
        "moveId": "sandstorm"
      },
      {
        "moveId": "scaryface"
      },
      {
        "moveId": "sleeptalk"
      },
      {
        "moveId": "smackdown"
      },
      {
        "moveId": "snowscape"
      },
      {
        "moveId": "stealthrock"
      },
      {
        "moveId": "stompingtantrum"
      },
      {
        "moveId": "stoneedge"
      },
      {
        "moveId": "strength"
      },
      {
        "moveId": "substitute"
      },
      {
        "moveId": "superpower"
      },
      {
        "moveId": "takedown"
      },
      {
        "moveId": "terablast"
      },
      {
        "moveId": "throatchop"
      },
      {
        "moveId": "trailblaze"
      }
    ],
    "tutor": [
      {
        "moveId": "ancientpower"
      },
      {
        "moveId": "babydolleyes"
      },
      {
        "moveId": "bulldoze"
      },
      {
        "moveId": "earthpower"
      },
      {
        "moveId": "endeavor"
      },
      {
        "moveId": "gigaimpact"
      },
      {
        "moveId": "highhorsepower"
      },
      {
        "moveId": "hyperbeam"
      },
      {
        "moveId": "icebeam"
      },
      {
        "moveId": "icefang"
      },
      {
        "moveId": "icywind"
      },
      {
        "moveId": "mudslap"
      },
      {
        "moveId": "rest"
      },
      {
        "moveId": "rockslide"
      },
      {
        "moveId": "rocksmash"
      },
      {
        "moveId": "sleeptalk"
      },
      {
        "moveId": "stealthrock"
      },
      {
        "moveId": "stompingtantrum"
      },
      {
        "moveId": "stoneedge"
      },
      {
        "moveId": "superpower"
      },
      {
        "moveId": "throatchop"
      }
    ],
    "legacy": [
      {
        "moveId": "attract"
      },
      {
        "moveId": "captivate"
      },
      {
        "moveId": "confide"
      },
      {
        "moveId": "defensecurl"
      },
      {
        "moveId": "detect"
      },
      {
        "moveId": "doubleteam"
      },
      {
        "moveId": "frustration"
      },
      {
        "moveId": "hiddenpower"
      },
      {
        "moveId": "hornattack"
      },
      {
        "moveId": "lightscreen"
      },
      {
        "moveId": "mimic"
      },
      {
        "moveId": "naturalgift"
      },
      {
        "moveId": "reflect"
      },
      {
        "moveId": "return"
      },
      {
        "moveId": "round"
      },
      {
        "moveId": "secretpower"
      },
      {
        "moveId": "snore"
      },
      {
        "moveId": "swagger"
      },
      {
        "moveId": "toxic"
      }
    ],
    "other": []
  },
  "evolutions": [
    {
      "targetKey": "cobblemon:mamoswine",
      "targetSlug": "mamoswine",
      "summary": "Nivel · Conoce ancientpower",
      "variant": "level_up"
    }
  ],
  "evolvesFrom": "swinub",
  "matchup": {
    "weakTo": [
      {
        "type": "fighting",
        "multiplier": 2
      },
      {
        "type": "fire",
        "multiplier": 2
      },
      {
        "type": "grass",
        "multiplier": 2
      },
      {
        "type": "steel",
        "multiplier": 2
      },
      {
        "type": "water",
        "multiplier": 2
      }
    ],
    "resists": [
      {
        "type": "poison",
        "multiplier": 0.5
      }
    ],
    "immuneTo": [
      "electric"
    ]
  },
  "image": {
    "kind": "sprite",
    "url": "https://raw.githubusercontent.com/PokeAPI/sprites/master/sprites/pokemon/other/official-artwork/221.png"
  },
  "spawnInfo": [
    {
      "biomes": [
        "#cobblemon:is_tundra"
      ],
      "bucket": "common",
      "level": "33-45",
      "timeRange": null,
      "sourceId": "cobblemon-core"
    },
    {
      "biomes": [
        "the_void"
      ],
      "bucket": "common",
      "level": "33-45",
      "timeRange": null,
      "sourceId": "digimod"
    },
    {
      "biomes": [
        "#cobblemon:is_tundra"
      ],
      "bucket": "common",
      "level": "33-45",
      "timeRange": null,
      "sourceId": "digimod-spawn-together"
    }
  ],
  "sourceMods": [
    "cobblemon-core",
    "lasers-additions"
  ],
  "primarySource": "cobblemon-core",
  "provenance": {
    "implemented": "cobblemon-core",
    "nationalPokedexNumber": "cobblemon-core",
    "name": "cobblemon-core",
    "primaryType": "cobblemon-core",
    "secondaryType": "cobblemon-core",
    "maleRatio": "cobblemon-core",
    "height": "cobblemon-core",
    "weight": "cobblemon-core",
    "pokedex": "cobblemon-core",
    "labels": "cobblemon-core",
    "aspects": "cobblemon-core",
    "abilities": "lasers-additions",
    "eggGroups": "cobblemon-core",
    "baseStats": "cobblemon-core",
    "evYield": "cobblemon-core",
    "baseExperienceYield": "cobblemon-core",
    "experienceGroup": "cobblemon-core",
    "catchRate": "cobblemon-core",
    "eggCycles": "cobblemon-core",
    "baseFriendship": "cobblemon-core",
    "baseScale": "cobblemon-core",
    "hitbox": "cobblemon-core",
    "riding": "cobblemon-core",
    "behaviour": "cobblemon-core",
    "drops": "cobblemon-core",
    "moves": "cobblemon-core",
    "preEvolution": "cobblemon-core",
    "evolutions": "cobblemon-core"
  }
}