{
  "id": "cobblemon:tirtouga",
  "namespace": "cobblemon",
  "slug": "tirtouga",
  "name": "Tirtouga",
  "nationalPokedexNumber": 564,
  "primaryType": "water",
  "secondaryType": "rock",
  "types": [
    "water",
    "rock"
  ],
  "baseStats": {
    "hp": 54,
    "attack": 78,
    "defence": 103,
    "special_attack": 53,
    "special_defence": 45,
    "speed": 22
  },
  "baseStatTotal": 355,
  "abilities": [
    "solidrock",
    "sturdy"
  ],
  "hiddenAbilities": [
    "swiftswim"
  ],
  "eggGroups": [
    "water_1",
    "water_3"
  ],
  "catchRate": 45,
  "eggCycles": 30,
  "baseFriendship": 50,
  "height": 7,
  "weight": 165,
  "maleRatio": 0.875,
  "experienceGroup": "medium_fast",
  "baseExperienceYield": 71,
  "labels": [
    "gen5",
    "fossil"
  ],
  "aspects": [],
  "forms": [],
  "pokedexDescription": "Restored from a fossil, this Pokémon can dive to depths beyond half a mile.",
  "moveset": {
    "levelUp": [
      {
        "moveId": "bide",
        "level": 1
      },
      {
        "moveId": "withdraw",
        "level": 1
      },
      {
        "moveId": "watergun",
        "level": 1
      },
      {
        "moveId": "protect",
        "level": 3
      },
      {
        "moveId": "aquajet",
        "level": 6
      },
      {
        "moveId": "smackdown",
        "level": 9
      },
      {
        "moveId": "ancientpower",
        "level": 12
      },
      {
        "moveId": "bite",
        "level": 15
      },
      {
        "moveId": "wideguard",
        "level": 18
      },
      {
        "moveId": "brine",
        "level": 21
      },
      {
        "moveId": "rockslide",
        "level": 24
      },
      {
        "moveId": "crunch",
        "level": 27
      },
      {
        "moveId": "curse",
        "level": 30
      },
      {
        "moveId": "irondefense",
        "level": 33
      },
      {
        "moveId": "guardpress",
        "level": 33
      },
      {
        "moveId": "aquatail",
        "level": 36
      },
      {
        "moveId": "raindance",
        "level": 39
      },
      {
        "moveId": "hydropump",
        "level": 42
      },
      {
        "moveId": "shellsmash",
        "level": 45
      }
    ],
    "egg": [
      {
        "moveId": "bide"
      },
      {
        "moveId": "block"
      },
      {
        "moveId": "flail"
      },
      {
        "moveId": "knockoff"
      },
      {
        "moveId": "rockthrow"
      },
      {
        "moveId": "rollout"
      },
      {
        "moveId": "slam"
      },
      {
        "moveId": "waterpulse"
      }
    ],
    "tm": [
      {
        "moveId": "ancientpower"
      },
      {
        "moveId": "aquatail"
      },
      {
        "moveId": "blizzard"
      },
      {
        "moveId": "block"
      },
      {
        "moveId": "bodyslam"
      },
      {
        "moveId": "brine"
      },
      {
        "moveId": "bulldoze"
      },
      {
        "moveId": "crunch"
      },
      {
        "moveId": "curse"
      },
      {
        "moveId": "dig"
      },
      {
        "moveId": "dive"
      },
      {
        "moveId": "earthpower"
      },
      {
        "moveId": "earthquake"
      },
      {
        "moveId": "endure"
      },
      {
        "moveId": "facade"
      },
      {
        "moveId": "guardpress"
      },
      {
        "moveId": "guardswap"
      },
      {
        "moveId": "hydropump"
      },
      {
        "moveId": "icebeam"
      },
      {
        "moveId": "icywind"
      },
      {
        "moveId": "irondefense"
      },
      {
        "moveId": "irontail"
      },
      {
        "moveId": "knockoff"
      },
      {
        "moveId": "liquidation"
      },
      {
        "moveId": "meteorbeam"
      },
      {
        "moveId": "mudshot"
      },
      {
        "moveId": "muddywater"
      },
      {
        "moveId": "protect"
      },
      {
        "moveId": "raindance"
      },
      {
        "moveId": "rest"
      },
      {
        "moveId": "rockblast"
      },
      {
        "moveId": "rockpolish"
      },
      {
        "moveId": "rockslide"
      },
      {
        "moveId": "rocksmash"
      },
      {
        "moveId": "rocktomb"
      },
      {
        "moveId": "rollout"
      },
      {
        "moveId": "sandstorm"
      },
      {
        "moveId": "scald"
      },
      {
        "moveId": "sleeptalk"
      },
      {
        "moveId": "smackdown"
      },
      {
        "moveId": "stealthrock"
      },
      {
        "moveId": "stoneedge"
      },
      {
        "moveId": "strength"
      },
      {
        "moveId": "substitute"
      },
      {
        "moveId": "surf"
      },
      {
        "moveId": "terablast"
      },
      {
        "moveId": "waterpulse"
      },
      {
        "moveId": "waterfall"
      },
      {
        "moveId": "whirlpool"
      },
      {
        "moveId": "zenheadbutt"
      }
    ],
    "tutor": [
      {
        "moveId": "ancientpower"
      },
      {
        "moveId": "aquatail"
      },
      {
        "moveId": "block"
      },
      {
        "moveId": "bulldoze"
      },
      {
        "moveId": "dive"
      },
      {
        "moveId": "earthpower"
      },
      {
        "moveId": "icebeam"
      },
      {
        "moveId": "icywind"
      },
      {
        "moveId": "irondefense"
      },
      {
        "moveId": "irontail"
      },
      {
        "moveId": "knockoff"
      },
      {
        "moveId": "liquidation"
      },
      {
        "moveId": "meteorbeam"
      },
      {
        "moveId": "rest"
      },
      {
        "moveId": "rockslide"
      },
      {
        "moveId": "rocksmash"
      },
      {
        "moveId": "rollout"
      },
      {
        "moveId": "sleeptalk"
      },
      {
        "moveId": "stealthrock"
      },
      {
        "moveId": "stoneedge"
      },
      {
        "moveId": "waterpulse"
      },
      {
        "moveId": "zenheadbutt"
      }
    ],
    "legacy": [
      {
        "moveId": "attract"
      },
      {
        "moveId": "confide"
      },
      {
        "moveId": "doubleteam"
      },
      {
        "moveId": "frustration"
      },
      {
        "moveId": "hiddenpower"
      },
      {
        "moveId": "return"
      },
      {
        "moveId": "round"
      },
      {
        "moveId": "secretpower"
      },
      {
        "moveId": "snore"
      },
      {
        "moveId": "swagger"
      },
      {
        "moveId": "toxic"
      }
    ],
    "other": []
  },
  "evolutions": [
    {
      "targetKey": "cobblemon:carracosta",
      "targetSlug": "carracosta",
      "summary": "Nivel · Nv. 37",
      "variant": "level_up"
    }
  ],
  "evolvesFrom": null,
  "matchup": {
    "weakTo": [
      {
        "type": "grass",
        "multiplier": 4
      },
      {
        "type": "electric",
        "multiplier": 2
      },
      {
        "type": "fighting",
        "multiplier": 2
      },
      {
        "type": "ground",
        "multiplier": 2
      }
    ],
    "resists": [
      {
        "type": "fire",
        "multiplier": 0.25
      },
      {
        "type": "flying",
        "multiplier": 0.5
      },
      {
        "type": "ice",
        "multiplier": 0.5
      },
      {
        "type": "normal",
        "multiplier": 0.5
      },
      {
        "type": "poison",
        "multiplier": 0.5
      }
    ],
    "immuneTo": []
  },
  "image": {
    "kind": "sprite",
    "url": "https://raw.githubusercontent.com/PokeAPI/sprites/master/sprites/pokemon/other/official-artwork/564.png"
  },
  "spawnInfo": [
    {
      "biomes": [
        "#cobblemon:is_lush"
      ],
      "bucket": "ultra-rare",
      "level": "15-40",
      "timeRange": null,
      "sourceId": "cobblemon-core"
    },
    {
      "biomes": [
        "#cobblemon:is_lush"
      ],
      "bucket": "ultra-rare",
      "level": "15-40",
      "timeRange": null,
      "sourceId": "cobblemon-core"
    },
    {
      "biomes": [
        "the_void"
      ],
      "bucket": "ultra-rare",
      "level": "15-40",
      "timeRange": null,
      "sourceId": "digimod"
    },
    {
      "biomes": [
        "the_void"
      ],
      "bucket": "ultra-rare",
      "level": "15-40",
      "timeRange": null,
      "sourceId": "digimod"
    },
    {
      "biomes": [
        "#cobblemon:is_lush"
      ],
      "bucket": "ultra-rare",
      "level": "15-40",
      "timeRange": null,
      "sourceId": "digimod-spawn-together"
    },
    {
      "biomes": [
        "#cobblemon:is_lush"
      ],
      "bucket": "ultra-rare",
      "level": "15-40",
      "timeRange": null,
      "sourceId": "digimod-spawn-together"
    }
  ],
  "sourceMods": [
    "cobblemon-core",
    "lasers-additions"
  ],
  "primarySource": "cobblemon-core",
  "provenance": {
    "implemented": "cobblemon-core",
    "nationalPokedexNumber": "cobblemon-core",
    "name": "cobblemon-core",
    "primaryType": "cobblemon-core",
    "secondaryType": "cobblemon-core",
    "maleRatio": "cobblemon-core",
    "height": "cobblemon-core",
    "weight": "cobblemon-core",
    "pokedex": "cobblemon-core",
    "labels": "cobblemon-core",
    "aspects": "cobblemon-core",
    "abilities": "cobblemon-core",
    "eggGroups": "cobblemon-core",
    "baseStats": "cobblemon-core",
    "evYield": "cobblemon-core",
    "baseExperienceYield": "cobblemon-core",
    "experienceGroup": "cobblemon-core",
    "catchRate": "cobblemon-core",
    "eggCycles": "cobblemon-core",
    "baseFriendship": "cobblemon-core",
    "baseScale": "cobblemon-core",
    "hitbox": "cobblemon-core",
    "behaviour": "cobblemon-core",
    "drops": "cobblemon-core",
    "moves": "lasers-additions",
    "evolutions": "cobblemon-core"
  }
}