{
  "id": "cobblemon:vulpix",
  "namespace": "cobblemon",
  "slug": "vulpix",
  "name": "Vulpix",
  "nationalPokedexNumber": 37,
  "primaryType": "fire",
  "secondaryType": null,
  "types": [
    "fire"
  ],
  "baseStats": {
    "hp": 38,
    "attack": 41,
    "defence": 40,
    "special_attack": 50,
    "special_defence": 65,
    "speed": 65
  },
  "baseStatTotal": 299,
  "abilities": [
    "flashfire"
  ],
  "hiddenAbilities": [
    "drought"
  ],
  "eggGroups": [
    "field"
  ],
  "catchRate": 190,
  "eggCycles": 20,
  "baseFriendship": 50,
  "height": 6,
  "weight": 99,
  "maleRatio": 0.25,
  "experienceGroup": "medium_fast",
  "baseExperienceYield": 60,
  "labels": [
    "gen1",
    "kantonian_form"
  ],
  "aspects": [],
  "forms": [
    {
      "name": "Alola",
      "aspects": [
        "alolan"
      ],
      "primaryType": "ice",
      "secondaryType": null,
      "types": [
        "ice"
      ],
      "battleOnly": false,
      "baseStats": null,
      "baseStatTotal": null,
      "abilities": [
        "snowcloak",
        "mistrider"
      ],
      "hiddenAbilities": [
        "snowwarning"
      ],
      "pokedexDescription": "They live together in a skulk, helping one another. Before eating their prey, they freeze it solid with their –58 degree Fahrenheit breath.",
      "moveset": {
        "levelUp": [
          {
            "moveId": "powdersnow",
            "level": 1
          },
          {
            "moveId": "tailwhip",
            "level": 1
          },
          {
            "moveId": "disable",
            "level": 4
          },
          {
            "moveId": "iceshard",
            "level": 8
          },
          {
            "moveId": "spite",
            "level": 12
          },
          {
            "moveId": "icywind",
            "level": 16
          },
          {
            "moveId": "confuseray",
            "level": 20
          },
          {
            "moveId": "aurorabeam",
            "level": 24
          },
          {
            "moveId": "chillout",
            "level": 24
          },
          {
            "moveId": "extrasensory",
            "level": 28
          },
          {
            "moveId": "icebeam",
            "level": 32
          },
          {
            "moveId": "imprison",
            "level": 36
          },
          {
            "moveId": "mist",
            "level": 40
          },
          {
            "moveId": "auroraveil",
            "level": 44
          },
          {
            "moveId": "freezedry",
            "level": 48
          },
          {
            "moveId": "grudge",
            "level": 52
          }
        ],
        "egg": [
          {
            "moveId": "babydolleyes"
          },
          {
            "moveId": "captivate"
          },
          {
            "moveId": "disable"
          },
          {
            "moveId": "extrasensory"
          },
          {
            "moveId": "feintattack"
          },
          {
            "moveId": "flail"
          },
          {
            "moveId": "freezedry"
          },
          {
            "moveId": "howl"
          },
          {
            "moveId": "hypnosis"
          },
          {
            "moveId": "moonblast"
          },
          {
            "moveId": "roar"
          },
          {
            "moveId": "secretpower"
          },
          {
            "moveId": "sheercold"
          }
        ],
        "tm": [
          {
            "moveId": "agility"
          },
          {
            "moveId": "auroraveil"
          },
          {
            "moveId": "babydolleyes"
          },
          {
            "moveId": "batonpass"
          },
          {
            "moveId": "blizzard"
          },
          {
            "moveId": "bodyslam"
          },
          {
            "moveId": "captivate"
          },
          {
            "moveId": "charm"
          },
          {
            "moveId": "chillout"
          },
          {
            "moveId": "chillingwater"
          },
          {
            "moveId": "confuseray"
          },
          {
            "moveId": "covet"
          },
          {
            "moveId": "darkpulse"
          },
          {
            "moveId": "dazzlinggleam"
          },
          {
            "moveId": "deepfreeze"
          },
          {
            "moveId": "dig"
          },
          {
            "moveId": "disarmingvoice"
          },
          {
            "moveId": "doubleedge"
          },
          {
            "moveId": "drainingkiss"
          },
          {
            "moveId": "encore"
          },
          {
            "moveId": "endure"
          },
          {
            "moveId": "facade"
          },
          {
            "moveId": "faketears"
          },
          {
            "moveId": "foulplay"
          },
          {
            "moveId": "frostbreath"
          },
          {
            "moveId": "hail"
          },
          {
            "moveId": "healbell"
          },
          {
            "moveId": "helpinghand"
          },
          {
            "moveId": "hex"
          },
          {
            "moveId": "icebeam"
          },
          {
            "moveId": "iciclespear"
          },
          {
            "moveId": "icywind"
          },
          {
            "moveId": "imprison"
          },
          {
            "moveId": "irontail"
          },
          {
            "moveId": "mistyterrain"
          },
          {
            "moveId": "nastyplot"
          },
          {
            "moveId": "painsplit"
          },
          {
            "moveId": "payback"
          },
          {
            "moveId": "playrough"
          },
          {
            "moveId": "powerswap"
          },
          {
            "moveId": "protect"
          },
          {
            "moveId": "psychup"
          },
          {
            "moveId": "raindance"
          },
          {
            "moveId": "rest"
          },
          {
            "moveId": "roar"
          },
          {
            "moveId": "roleplay"
          },
          {
            "moveId": "safeguard"
          },
          {
            "moveId": "secretpower"
          },
          {
            "moveId": "sleeptalk"
          },
          {
            "moveId": "snowscape"
          },
          {
            "moveId": "spite"
          },
          {
            "moveId": "storedpower"
          },
          {
            "moveId": "substitute"
          },
          {
            "moveId": "swift"
          },
          {
            "moveId": "tailslap"
          },
          {
            "moveId": "takedown"
          },
          {
            "moveId": "terablast"
          },
          {
            "moveId": "weatherball"
          },
          {
            "moveId": "zenheadbutt"
          }
        ],
        "tutor": [
          {
            "moveId": "babydolleyes"
          },
          {
            "moveId": "covet"
          },
          {
            "moveId": "darkpulse"
          },
          {
            "moveId": "dazzlinggleam"
          },
          {
            "moveId": "foulplay"
          },
          {
            "moveId": "healbell"
          },
          {
            "moveId": "helpinghand"
          },
          {
            "moveId": "icebeam"
          },
          {
            "moveId": "icywind"
          },
          {
            "moveId": "irontail"
          },
          {
            "moveId": "painsplit"
          },
          {
            "moveId": "playrough"
          },
          {
            "moveId": "rest"
          },
          {
            "moveId": "roleplay"
          },
          {
            "moveId": "sleeptalk"
          },
          {
            "moveId": "spite"
          },
          {
            "moveId": "swift"
          },
          {
            "moveId": "zenheadbutt"
          }
        ],
        "legacy": [
          {
            "moveId": "aquatail"
          },
          {
            "moveId": "attract"
          },
          {
            "moveId": "confide"
          },
          {
            "moveId": "doubleteam"
          },
          {
            "moveId": "frustration"
          },
          {
            "moveId": "headbutt"
          },
          {
            "moveId": "hiddenpower"
          },
          {
            "moveId": "reflect"
          },
          {
            "moveId": "return"
          },
          {
            "moveId": "round"
          },
          {
            "moveId": "snore"
          },
          {
            "moveId": "swagger"
          },
          {
            "moveId": "tackle"
          },
          {
            "moveId": "toxic"
          }
        ],
        "other": [
          {
            "moveId": "celebrate"
          }
        ]
      },
      "matchup": {
        "weakTo": [
          {
            "type": "fighting",
            "multiplier": 2
          },
          {
            "type": "fire",
            "multiplier": 2
          },
          {
            "type": "rock",
            "multiplier": 2
          },
          {
            "type": "steel",
            "multiplier": 2
          }
        ],
        "resists": [
          {
            "type": "ice",
            "multiplier": 0.5
          }
        ],
        "immuneTo": []
      },
      "evolutions": [
        {
          "targetKey": "cobblemon:ninetales",
          "targetSlug": "ninetales-alola",
          "summary": "Usar ice_stone · variante alolan",
          "variant": "item_interact"
        }
      ],
      "slug": "vulpix-alola"
    }
  ],
  "pokedexDescription": "Inside Vulpix's body burns a flame that never goes out. During the daytime, when the temperatures rise, this Pokémon releases flames from its mouth to prevent its body from growing too hot.",
  "moveset": {
    "levelUp": [
      {
        "moveId": "ember",
        "level": 1
      },
      {
        "moveId": "tailwhip",
        "level": 1
      },
      {
        "moveId": "disable",
        "level": 4
      },
      {
        "moveId": "quickattack",
        "level": 8
      },
      {
        "moveId": "spite",
        "level": 12
      },
      {
        "moveId": "incinerate",
        "level": 16
      },
      {
        "moveId": "confuseray",
        "level": 20
      },
      {
        "moveId": "willowisp",
        "level": 24
      },
      {
        "moveId": "flameburst",
        "level": 28
      },
      {
        "moveId": "flamethrower",
        "level": 32
      },
      {
        "moveId": "imprison",
        "level": 36
      },
      {
        "moveId": "firespin",
        "level": 40
      },
      {
        "moveId": "safeguard",
        "level": 44
      },
      {
        "moveId": "inferno",
        "level": 48
      },
      {
        "moveId": "grudge",
        "level": 52
      }
    ],
    "egg": [
      {
        "moveId": "babydolleyes"
      },
      {
        "moveId": "captivate"
      },
      {
        "moveId": "disable"
      },
      {
        "moveId": "extrasensory"
      },
      {
        "moveId": "feintattack"
      },
      {
        "moveId": "flail"
      },
      {
        "moveId": "flamecharge"
      },
      {
        "moveId": "healingwish"
      },
      {
        "moveId": "howl"
      },
      {
        "moveId": "hypnosis"
      },
      {
        "moveId": "memento"
      },
      {
        "moveId": "roar"
      },
      {
        "moveId": "secretpower"
      }
    ],
    "tm": [
      {
        "moveId": "agility"
      },
      {
        "moveId": "babydolleyes"
      },
      {
        "moveId": "batonpass"
      },
      {
        "moveId": "bodyslam"
      },
      {
        "moveId": "burningjealousy"
      },
      {
        "moveId": "captivate"
      },
      {
        "moveId": "charm"
      },
      {
        "moveId": "confuseray"
      },
      {
        "moveId": "covet"
      },
      {
        "moveId": "darkpulse"
      },
      {
        "moveId": "dig"
      },
      {
        "moveId": "doubleedge"
      },
      {
        "moveId": "encore"
      },
      {
        "moveId": "endure"
      },
      {
        "moveId": "energyball"
      },
      {
        "moveId": "facade"
      },
      {
        "moveId": "fireblast"
      },
      {
        "moveId": "firespin"
      },
      {
        "moveId": "flamecharge"
      },
      {
        "moveId": "flamethrower"
      },
      {
        "moveId": "flareblitz"
      },
      {
        "moveId": "foulplay"
      },
      {
        "moveId": "headbutt"
      },
      {
        "moveId": "heatwave"
      },
      {
        "moveId": "helpinghand"
      },
      {
        "moveId": "hex"
      },
      {
        "moveId": "imprison"
      },
      {
        "moveId": "incinerate"
      },
      {
        "moveId": "irontail"
      },
      {
        "moveId": "mysticalfire"
      },
      {
        "moveId": "nastyplot"
      },
      {
        "moveId": "ominouswind"
      },
      {
        "moveId": "overheat"
      },
      {
        "moveId": "painsplit"
      },
      {
        "moveId": "payback"
      },
      {
        "moveId": "powerswap"
      },
      {
        "moveId": "protect"
      },
      {
        "moveId": "psychup"
      },
      {
        "moveId": "rest"
      },
      {
        "moveId": "roar"
      },
      {
        "moveId": "roleplay"
      },
      {
        "moveId": "safeguard"
      },
      {
        "moveId": "secretpower"
      },
      {
        "moveId": "sleeptalk"
      },
      {
        "moveId": "snarl"
      },
      {
        "moveId": "spite"
      },
      {
        "moveId": "substitute"
      },
      {
        "moveId": "sunnyday"
      },
      {
        "moveId": "swift"
      },
      {
        "moveId": "tailslap"
      },
      {
        "moveId": "takedown"
      },
      {
        "moveId": "terablast"
      },
      {
        "moveId": "weatherball"
      },
      {
        "moveId": "willowisp"
      },
      {
        "moveId": "zenheadbutt"
      }
    ],
    "tutor": [
      {
        "moveId": "babydolleyes"
      },
      {
        "moveId": "burningjealousy"
      },
      {
        "moveId": "covet"
      },
      {
        "moveId": "darkpulse"
      },
      {
        "moveId": "energyball"
      },
      {
        "moveId": "flamethrower"
      },
      {
        "moveId": "foulplay"
      },
      {
        "moveId": "heatwave"
      },
      {
        "moveId": "helpinghand"
      },
      {
        "moveId": "irontail"
      },
      {
        "moveId": "mysticalfire"
      },
      {
        "moveId": "ominouswind"
      },
      {
        "moveId": "painsplit"
      },
      {
        "moveId": "rest"
      },
      {
        "moveId": "roleplay"
      },
      {
        "moveId": "sleeptalk"
      },
      {
        "moveId": "snarl"
      },
      {
        "moveId": "spite"
      },
      {
        "moveId": "swift"
      },
      {
        "moveId": "zenheadbutt"
      }
    ],
    "legacy": [
      {
        "moveId": "attract"
      },
      {
        "moveId": "bide"
      },
      {
        "moveId": "confide"
      },
      {
        "moveId": "curse"
      },
      {
        "moveId": "doubleteam"
      },
      {
        "moveId": "frustration"
      },
      {
        "moveId": "hiddenpower"
      },
      {
        "moveId": "mimic"
      },
      {
        "moveId": "naturalgift"
      },
      {
        "moveId": "rage"
      },
      {
        "moveId": "reflect"
      },
      {
        "moveId": "return"
      },
      {
        "moveId": "round"
      },
      {
        "moveId": "skullbash"
      },
      {
        "moveId": "snore"
      },
      {
        "moveId": "swagger"
      },
      {
        "moveId": "tackle"
      },
      {
        "moveId": "toxic"
      }
    ],
    "other": []
  },
  "evolutions": [
    {
      "targetKey": "cobblemon:ninetales",
      "targetSlug": "ninetales",
      "summary": "Usar fire_stone",
      "variant": "item_interact"
    }
  ],
  "evolvesFrom": null,
  "matchup": {
    "weakTo": [
      {
        "type": "ground",
        "multiplier": 2
      },
      {
        "type": "rock",
        "multiplier": 2
      },
      {
        "type": "water",
        "multiplier": 2
      }
    ],
    "resists": [
      {
        "type": "bug",
        "multiplier": 0.5
      },
      {
        "type": "fairy",
        "multiplier": 0.5
      },
      {
        "type": "fire",
        "multiplier": 0.5
      },
      {
        "type": "grass",
        "multiplier": 0.5
      },
      {
        "type": "ice",
        "multiplier": 0.5
      },
      {
        "type": "steel",
        "multiplier": 0.5
      }
    ],
    "immuneTo": []
  },
  "image": {
    "kind": "sprite",
    "url": "https://raw.githubusercontent.com/PokeAPI/sprites/master/sprites/pokemon/other/official-artwork/37.png"
  },
  "spawnInfo": [
    {
      "biomes": [
        "#cobblemon:is_forest",
        "#cobblemon:is_taiga"
      ],
      "bucket": "uncommon",
      "level": "5-30",
      "timeRange": null,
      "sourceId": "cobblemon-core"
    },
    {
      "biomes": [
        "#cobblemon:nether/is_forest"
      ],
      "bucket": "common",
      "level": "5-30",
      "timeRange": null,
      "sourceId": "cobblemon-core"
    },
    {
      "biomes": [
        "#cobblemon:is_snowy_forest",
        "#cobblemon:is_snowy_taiga"
      ],
      "bucket": "uncommon",
      "level": "5-30",
      "timeRange": null,
      "sourceId": "cobblemon-core"
    },
    {
      "biomes": [
        "#cobblemon:nether/is_frozen"
      ],
      "bucket": "common",
      "level": "5-30",
      "timeRange": null,
      "sourceId": "cobblemon-core"
    },
    {
      "biomes": [
        "the_void"
      ],
      "bucket": "uncommon",
      "level": "5-30",
      "timeRange": null,
      "sourceId": "digimod"
    },
    {
      "biomes": [
        "the_void"
      ],
      "bucket": "common",
      "level": "5-30",
      "timeRange": null,
      "sourceId": "digimod"
    },
    {
      "biomes": [
        "the_void"
      ],
      "bucket": "uncommon",
      "level": "5-30",
      "timeRange": null,
      "sourceId": "digimod"
    },
    {
      "biomes": [
        "the_void"
      ],
      "bucket": "common",
      "level": "5-30",
      "timeRange": null,
      "sourceId": "digimod"
    },
    {
      "biomes": [
        "#cobblemon:is_forest",
        "#cobblemon:is_taiga"
      ],
      "bucket": "uncommon",
      "level": "5-30",
      "timeRange": null,
      "sourceId": "digimod-spawn-together"
    },
    {
      "biomes": [
        "#cobblemon:nether/is_forest"
      ],
      "bucket": "common",
      "level": "5-30",
      "timeRange": null,
      "sourceId": "digimod-spawn-together"
    },
    {
      "biomes": [
        "#cobblemon:is_snowy_forest",
        "#cobblemon:is_snowy_taiga"
      ],
      "bucket": "uncommon",
      "level": "5-30",
      "timeRange": null,
      "sourceId": "digimod-spawn-together"
    },
    {
      "biomes": [
        "#cobblemon:nether/is_frozen"
      ],
      "bucket": "common",
      "level": "5-30",
      "timeRange": null,
      "sourceId": "digimod-spawn-together"
    }
  ],
  "sourceMods": [
    "cobblemon-core",
    "lasers-additions"
  ],
  "primarySource": "cobblemon-core",
  "provenance": {
    "implemented": "cobblemon-core",
    "nationalPokedexNumber": "cobblemon-core",
    "name": "cobblemon-core",
    "primaryType": "cobblemon-core",
    "maleRatio": "cobblemon-core",
    "height": "cobblemon-core",
    "weight": "cobblemon-core",
    "pokedex": "cobblemon-core",
    "labels": "cobblemon-core",
    "aspects": "cobblemon-core",
    "abilities": "cobblemon-core",
    "eggGroups": "cobblemon-core",
    "baseStats": "cobblemon-core",
    "evYield": "cobblemon-core",
    "baseExperienceYield": "cobblemon-core",
    "experienceGroup": "cobblemon-core",
    "catchRate": "cobblemon-core",
    "eggCycles": "cobblemon-core",
    "baseFriendship": "cobblemon-core",
    "features": "cobblemon-core",
    "baseScale": "cobblemon-core",
    "hitbox": "cobblemon-core",
    "behaviour": "cobblemon-core",
    "ai": "cobblemon-core",
    "drops": "cobblemon-core",
    "moves": "cobblemon-core",
    "evolutions": "cobblemon-core",
    "forms": "lasers-additions"
  }
}