{
  "id": "cobblemon:woobat",
  "namespace": "cobblemon",
  "slug": "woobat",
  "name": "Woobat",
  "nationalPokedexNumber": 527,
  "primaryType": "psychic",
  "secondaryType": "flying",
  "types": [
    "psychic",
    "flying"
  ],
  "baseStats": {
    "hp": 65,
    "attack": 45,
    "defence": 43,
    "special_attack": 55,
    "special_defence": 43,
    "speed": 72
  },
  "baseStatTotal": 323,
  "abilities": [
    "unaware",
    "klutz"
  ],
  "hiddenAbilities": [
    "simple"
  ],
  "eggGroups": [
    "field",
    "flying"
  ],
  "catchRate": 190,
  "eggCycles": 15,
  "baseFriendship": 50,
  "height": 4,
  "weight": 21,
  "maleRatio": 0.5,
  "experienceGroup": "medium_fast",
  "baseExperienceYield": 65,
  "labels": [
    "gen5"
  ],
  "aspects": [],
  "forms": [],
  "pokedexDescription": "The heart-shaped mark left on a body after a Woobat has been attached to it is said to bring good fortune.",
  "moveset": {
    "levelUp": [
      {
        "moveId": "odorsleuth",
        "level": 1
      },
      {
        "moveId": "gust",
        "level": 1
      },
      {
        "moveId": "attract",
        "level": 1
      },
      {
        "moveId": "confusion",
        "level": 5
      },
      {
        "moveId": "endeavor",
        "level": 10
      },
      {
        "moveId": "heartstamp",
        "level": 15
      },
      {
        "moveId": "imprison",
        "level": 20
      },
      {
        "moveId": "assurance",
        "level": 25
      },
      {
        "moveId": "amnesia",
        "level": 30
      },
      {
        "moveId": "psychicsnap",
        "level": 30
      },
      {
        "moveId": "airslash",
        "level": 35
      },
      {
        "moveId": "psychic",
        "level": 40
      },
      {
        "moveId": "calmmind",
        "level": 45
      },
      {
        "moveId": "futuresight",
        "level": 50
      },
      {
        "moveId": "simplebeam",
        "level": 55
      },
      {
        "moveId": "hypnoblast",
        "level": 60
      }
    ],
    "egg": [
      {
        "moveId": "captivate"
      },
      {
        "moveId": "flatter"
      },
      {
        "moveId": "knockoff"
      },
      {
        "moveId": "psychoshift"
      },
      {
        "moveId": "roost"
      },
      {
        "moveId": "supersonic"
      },
      {
        "moveId": "synchronoise"
      }
    ],
    "tm": [
      {
        "moveId": "acrobatics"
      },
      {
        "moveId": "aerialace"
      },
      {
        "moveId": "afteryou"
      },
      {
        "moveId": "aircutter"
      },
      {
        "moveId": "airslash"
      },
      {
        "moveId": "allyswitch"
      },
      {
        "moveId": "amnesia"
      },
      {
        "moveId": "assurance"
      },
      {
        "moveId": "attract"
      },
      {
        "moveId": "batonpass"
      },
      {
        "moveId": "calmmind"
      },
      {
        "moveId": "captivate"
      },
      {
        "moveId": "chargebeam"
      },
      {
        "moveId": "charm"
      },
      {
        "moveId": "defog"
      },
      {
        "moveId": "dreameater"
      },
      {
        "moveId": "dualwingbeat"
      },
      {
        "moveId": "embargo"
      },
      {
        "moveId": "endeavor"
      },
      {
        "moveId": "endure"
      },
      {
        "moveId": "energyball"
      },
      {
        "moveId": "expandingforce"
      },
      {
        "moveId": "facade"
      },
      {
        "moveId": "faketears"
      },
      {
        "moveId": "flash"
      },
      {
        "moveId": "fly"
      },
      {
        "moveId": "futuresight"
      },
      {
        "moveId": "gigadrain"
      },
      {
        "moveId": "gyroball"
      },
      {
        "moveId": "heatwave"
      },
      {
        "moveId": "helpinghand"
      },
      {
        "moveId": "hypnoblast"
      },
      {
        "moveId": "imprison"
      },
      {
        "moveId": "knockoff"
      },
      {
        "moveId": "lightscreen"
      },
      {
        "moveId": "magiccoat"
      },
      {
        "moveId": "nastyplot"
      },
      {
        "moveId": "pluck"
      },
      {
        "moveId": "protect"
      },
      {
        "moveId": "psychup"
      },
      {
        "moveId": "psychic"
      },
      {
        "moveId": "psychicsnap"
      },
      {
        "moveId": "psychocut"
      },
      {
        "moveId": "psyshock"
      },
      {
        "moveId": "raindance"
      },
      {
        "moveId": "reflect"
      },
      {
        "moveId": "rest"
      },
      {
        "moveId": "roost"
      },
      {
        "moveId": "safeguard"
      },
      {
        "moveId": "shadowball"
      },
      {
        "moveId": "shockwave"
      },
      {
        "moveId": "signalbeam"
      },
      {
        "moveId": "skillswap"
      },
      {
        "moveId": "sleeptalk"
      },
      {
        "moveId": "speedswap"
      },
      {
        "moveId": "steelwing"
      },
      {
        "moveId": "storedpower"
      },
      {
        "moveId": "substitute"
      },
      {
        "moveId": "superfang"
      },
      {
        "moveId": "swift"
      },
      {
        "moveId": "tailwind"
      },
      {
        "moveId": "taunt"
      },
      {
        "moveId": "telekinesis"
      },
      {
        "moveId": "terablast"
      },
      {
        "moveId": "thief"
      },
      {
        "moveId": "thunderwave"
      },
      {
        "moveId": "torment"
      },
      {
        "moveId": "trick"
      },
      {
        "moveId": "trickroom"
      },
      {
        "moveId": "uturn"
      },
      {
        "moveId": "uproar"
      },
      {
        "moveId": "venomdrench"
      },
      {
        "moveId": "zenheadbutt"
      }
    ],
    "tutor": [
      {
        "moveId": "aerialace"
      },
      {
        "moveId": "afteryou"
      },
      {
        "moveId": "aircutter"
      },
      {
        "moveId": "allyswitch"
      },
      {
        "moveId": "calmmind"
      },
      {
        "moveId": "chargebeam"
      },
      {
        "moveId": "defog"
      },
      {
        "moveId": "dualwingbeat"
      },
      {
        "moveId": "endeavor"
      },
      {
        "moveId": "energyball"
      },
      {
        "moveId": "expandingforce"
      },
      {
        "moveId": "gigadrain"
      },
      {
        "moveId": "heatwave"
      },
      {
        "moveId": "helpinghand"
      },
      {
        "moveId": "knockoff"
      },
      {
        "moveId": "magiccoat"
      },
      {
        "moveId": "psychic"
      },
      {
        "moveId": "psychocut"
      },
      {
        "moveId": "rest"
      },
      {
        "moveId": "roost"
      },
      {
        "moveId": "shadowball"
      },
      {
        "moveId": "shockwave"
      },
      {
        "moveId": "signalbeam"
      },
      {
        "moveId": "skillswap"
      },
      {
        "moveId": "sleeptalk"
      },
      {
        "moveId": "superfang"
      },
      {
        "moveId": "swift"
      },
      {
        "moveId": "tailwind"
      },
      {
        "moveId": "telekinesis"
      },
      {
        "moveId": "trick"
      },
      {
        "moveId": "uproar"
      },
      {
        "moveId": "zenheadbutt"
      }
    ],
    "legacy": [
      {
        "moveId": "confide"
      },
      {
        "moveId": "doubleteam"
      },
      {
        "moveId": "frustration"
      },
      {
        "moveId": "hiddenpower"
      },
      {
        "moveId": "return"
      },
      {
        "moveId": "round"
      },
      {
        "moveId": "secretpower"
      },
      {
        "moveId": "snore"
      },
      {
        "moveId": "swagger"
      },
      {
        "moveId": "toxic"
      }
    ],
    "other": []
  },
  "evolutions": [
    {
      "targetKey": "cobblemon:swoobat",
      "targetSlug": "swoobat",
      "summary": "Nivel · Amistad 160+",
      "variant": "level_up"
    }
  ],
  "evolvesFrom": null,
  "matchup": {
    "weakTo": [
      {
        "type": "dark",
        "multiplier": 2
      },
      {
        "type": "electric",
        "multiplier": 2
      },
      {
        "type": "ghost",
        "multiplier": 2
      },
      {
        "type": "ice",
        "multiplier": 2
      },
      {
        "type": "rock",
        "multiplier": 2
      }
    ],
    "resists": [
      {
        "type": "fighting",
        "multiplier": 0.25
      },
      {
        "type": "grass",
        "multiplier": 0.5
      },
      {
        "type": "psychic",
        "multiplier": 0.5
      }
    ],
    "immuneTo": [
      "ground"
    ]
  },
  "image": {
    "kind": "sprite",
    "url": "https://raw.githubusercontent.com/PokeAPI/sprites/master/sprites/pokemon/other/official-artwork/527.png"
  },
  "spawnInfo": [
    {
      "biomes": [
        "#cobblemon:is_jungle",
        "#cobblemon:is_savanna"
      ],
      "bucket": "common",
      "level": "7-32",
      "timeRange": "night",
      "sourceId": "cobblemon-core"
    },
    {
      "biomes": [
        "#cobblemon:is_jungle",
        "#cobblemon:is_savanna"
      ],
      "bucket": "common",
      "level": "7-32",
      "timeRange": null,
      "sourceId": "cobblemon-core"
    },
    {
      "biomes": [
        "the_void"
      ],
      "bucket": "common",
      "level": "7-32",
      "timeRange": "night",
      "sourceId": "digimod"
    },
    {
      "biomes": [
        "the_void"
      ],
      "bucket": "common",
      "level": "7-32",
      "timeRange": null,
      "sourceId": "digimod"
    },
    {
      "biomes": [
        "#cobblemon:is_jungle",
        "#cobblemon:is_savanna"
      ],
      "bucket": "common",
      "level": "7-32",
      "timeRange": "night",
      "sourceId": "digimod-spawn-together"
    },
    {
      "biomes": [
        "#cobblemon:is_jungle",
        "#cobblemon:is_savanna"
      ],
      "bucket": "common",
      "level": "7-32",
      "timeRange": null,
      "sourceId": "digimod-spawn-together"
    }
  ],
  "sourceMods": [
    "cobblemon-core",
    "lasers-additions"
  ],
  "primarySource": "cobblemon-core",
  "provenance": {
    "implemented": "cobblemon-core",
    "nationalPokedexNumber": "cobblemon-core",
    "name": "cobblemon-core",
    "primaryType": "cobblemon-core",
    "secondaryType": "cobblemon-core",
    "maleRatio": "cobblemon-core",
    "height": "cobblemon-core",
    "weight": "cobblemon-core",
    "pokedex": "cobblemon-core",
    "labels": "cobblemon-core",
    "aspects": "cobblemon-core",
    "abilities": "cobblemon-core",
    "eggGroups": "cobblemon-core",
    "baseStats": "cobblemon-core",
    "evYield": "cobblemon-core",
    "baseExperienceYield": "cobblemon-core",
    "experienceGroup": "cobblemon-core",
    "catchRate": "cobblemon-core",
    "eggCycles": "cobblemon-core",
    "baseFriendship": "cobblemon-core",
    "baseScale": "cobblemon-core",
    "hitbox": "cobblemon-core",
    "behaviour": "cobblemon-core",
    "drops": "cobblemon-core",
    "moves": "lasers-additions",
    "evolutions": "cobblemon-core"
  }
}